blogslicer/__init__.py
blogslicer/_nbdev.py
blogslicer/core.py
blogslicer/testargs.py
blogslicer-0.0.3.dist-info/LICENSE
blogslicer-0.0.3.dist-info/METADATA
blogslicer-0.0.3.dist-info/WHEEL
blogslicer-0.0.3.dist-info/top_level.txt
blogslicer-0.0.3.dist-info/RECORD
