Metadata-Version: 2.1
Name: blogslicer
Version: 0.0.3
Summary: Slices a single journal text-file into individual pages for Github Pages Jekyll blog publishing.
Home-page: https://github.com/miklevin/blogslicer/tree/main/
Author: Mike Levin
Author-email: miklevin@gmail.com
License: Apache Software License 2.0
Keywords: jekyll blog markdown slice
Platform: UNKNOWN
Classifier: Development Status :: 2 - Pre-Alpha
Classifier: Intended Audience :: Developers
Classifier: Natural Language :: English
Classifier: Programming Language :: Python :: 3.6
Classifier: Programming Language :: Python :: 3.7
Classifier: Programming Language :: Python :: 3.8
Classifier: License :: OSI Approved :: Apache Software License
Requires-Python: >=3.6
License-File: LICENSE
Requires-Dist: python-slugify
